Metadata-Version: 1.1
Name: calendarBot
Version: 0.1.2
Summary: Mattermost calendar Bot
Home-page: https://github.com/mharrend
Author: Marco A. Harrendorf
Author-email: marco.harrendorf@cern.ch
License: MIT
Keywords: chat bot calendar mattermost
Platform: Any
Classifier: Development Status :: 4 - Beta
Classifier: Intended Audience :: Developers
Classifier: Operating System :: OS Independent
Classifier: Programming Language :: Python :: 3
Classifier: Topic :: Internet :: WWW/HTTP
Classifier: Topic :: Software Development :: Libraries :: Python Modules
